py_pkg_playground/__init__.py
py_pkg_playground/example.py
py_pkg_playground/py.typed
py_pkg_playground-0.3.0.dist-info/LICENSE
py_pkg_playground-0.3.0.dist-info/WHEEL
py_pkg_playground-0.3.0.dist-info/METADATA
py_pkg_playground-0.3.0.dist-info/RECORD
