Metadata-Version: 2.1
Name: py-pkg-playground
Version: 0.3.0
Summary: This is a Python package to learn Github actions!
Home-page: https://github.com/Dresdn/py-pkg-playground
License: MIT
Requires-Python: >=3.6.2,<4.0.0
Classifier: Development Status :: 3 - Alpha
Classifier: Intended Audience :: Developers
Classifier: License :: OSI Approved :: MIT License
Classifier: Operating System :: OS Independent
Classifier: Programming Language :: Python :: 3
Classifier: Programming Language :: Python :: 3.7
Classifier: Programming Language :: Python :: 3.8
Classifier: Programming Language :: Python :: 3.9
Classifier: Topic :: Software Development :: Libraries :: Python Modules
Project-URL: Repository, https://github.com/Dresdn/py-pkg-playground
